{
  "placeholderImages": [
    {
      "id": "map-view",
      "description": "An artistic representation of a dense jungle.",
      "imageUrl": "https://images.unsplash.com/photo-1500534623283-312aade485b7?q=80&w=2070&auto=format&fit=crop",
      "imageHint": "jungle path"
    },
    {
      "id": "avatar-1",
      "description": "User avatar 1 - Tiger cub",
      "imageUrl": "https://images.unsplash.com/photo-1595163140502-1a4c8402f06b?q=80&w=2070&auto=format&fit=crop",
      "imageHint": "tiger cub"
    },
    {
      "id": "avatar-2",
      "description": "User avatar 2 - Leopard",
      "imageUrl": "https://images.unsplash.com/photo-1574100004472-e536d3b6bacc?q=80&w=2070&auto=format&fit=crop",
      "imageHint": "leopard portrait"
    },
    {
      "id": "avatar-3",
      "description": "User avatar 3 - Bear",
      "imageUrl": "https://images.unsplash.com/photo-1530584497972-23ce79b94065?q=80&w=2070&auto=format&fit=crop",
      "imageHint": "bear forest"
    },
    {
      "id": "avatar-4",
      "description": "User avatar 4 - Deer in a forest",
      "imageUrl": "https://images.unsplash.com/photo-1507563742695-a28ff7567d40?q=80&w=2070&auto=format&fit=crop",
      "imageHint": "deer forest"
    },
    {
      "id": "user-profile",
      "description": "Main user profile avatar - Majestic Tiger",
      "imageUrl": "https://images.unsplash.com/photo-1601758176586-253073289a38?q=80&w=1935&auto=format&fit=crop",
      "imageHint": "tiger face"
    },
    {
      "id": "hero-image",
      "description": "Hero image for the landing page - Tiger in its natural habitat",
      "imageUrl": "https://images.unsplash.com/photo-1551893478-d726eaf0442c?q=80&w=2070&auto=format&fit=crop",
      "imageHint": "tiger jungle"
    },
    {
      "id": "wildlife-collage",
      "description": "A collage of wildlife animals - A close-up of a tiger's face",
      "imageUrl": "https://images.unsplash.com/photo-1591823730310-85888355b0a3?q=80&w=2070&auto=format&fit=crop",
      "imageHint": "tiger face"
    },
    {
      "id": "tadoba-animals",
      "description": "An elephant in the wild.",
      "imageUrl": "https://images.unsplash.com/photo-1557050543-4d5f4e07ef46?q=80&w=1932&auto=format&fit=crop",
      "imageHint": "elephant wild"
    },
    {
      "id": "rangers-team",
      "description": "A majestic lion.",
      "imageUrl": "https://images.unsplash.com/photo-1614027164847-1b28acc1bb1f?q=80&w=2070&auto=format&fit=crop",
      "imageHint": "lion face"
    },
    {
      "id": "login-background",
      "description": "Jungle background for login page.",
      "imageUrl": "https://images.unsplash.com/photo-1500534623283-312aade485b7?q=80&w=2070&auto=format&fit=crop",
      "imageHint": "jungle path"
    },
    {
      "id": "dashboard-background",
      "description": "Misty jungle background for dashboard.",
      "imageUrl": "https://images.unsplash.com/photo-1447752875215-b2761acb3c5d?q=80&w=2070&auto=format&fit=crop",
      "imageHint": "misty jungle"
    }
  ]
}